async_igvf_client/__init__.py
async_igvf_client/api_client.py
async_igvf_client/api_response.py
async_igvf_client/configuration.py
async_igvf_client/exceptions.py
async_igvf_client/py.typed
async_igvf_client/rest.py
async_igvf_client/api/__init__.py
async_igvf_client/api/async_igvf_api.py
async_igvf_client/models/__init__.py
async_igvf_client/models/access_key.py
async_igvf_client/models/access_key_results.py
async_igvf_client/models/alignment_file.py
async_igvf_client/models/alignment_file_results.py
async_igvf_client/models/analysis_set.py
async_igvf_client/models/analysis_set_results.py
async_igvf_client/models/analysis_step.py
async_igvf_client/models/analysis_step_results.py
async_igvf_client/models/analysis_step_version.py
async_igvf_client/models/analysis_step_version_results.py
async_igvf_client/models/assay_term.py
async_igvf_client/models/assay_term_results.py
async_igvf_client/models/attachment.py
async_igvf_client/models/attachment1.py
async_igvf_client/models/auxiliary_set.py
async_igvf_client/models/auxiliary_set_results.py
async_igvf_client/models/award.py
async_igvf_client/models/award_results.py
async_igvf_client/models/biomarker.py
async_igvf_client/models/biomarker_results.py
async_igvf_client/models/configuration_file.py
async_igvf_client/models/configuration_file_results.py
async_igvf_client/models/construct_library_set.py
async_igvf_client/models/construct_library_set_results.py
async_igvf_client/models/crispr_modification.py
async_igvf_client/models/crispr_modification_results.py
async_igvf_client/models/curated_set.py
async_igvf_client/models/curated_set_results.py
async_igvf_client/models/degron_modification.py
async_igvf_client/models/degron_modification_results.py
async_igvf_client/models/document.py
async_igvf_client/models/document_results.py
async_igvf_client/models/gene.py
async_igvf_client/models/gene_location.py
async_igvf_client/models/gene_location1.py
async_igvf_client/models/gene_results.py
igvf_async_client-107.0.1.dist-info/licenses/LICENSE
igvf_async_client-107.0.1.dist-info/METADATA
igvf_async_client-107.0.1.dist-info/WHEEL
igvf_async_client-107.0.1.dist-info/top_level.txt
igvf_async_client-107.0.1.dist-info/RECORD
